{
    "imdbRating": 8.3,
    "imdbVotes": 108973,
    "imdbId": "tt0041959",
    "title": "The Third Man",
    "year": 1949,
    "rated": "NOT RATED",
    "released": "31 Aug 1949",
    "runtime": "93 min",
    "genre": [
        "Film-Noir",
        "Mystery",
        "Thriller"
    ],
    "director": "Carol Reed",
    "writer": "Graham Greene (by), Graham Greene (screen play)",
    "actors": [
        ""
    ],
    "plot": "Pulp novelist Holly Martins travels to shadowy, postwar Vienna, only to find himself investigating the mysterious death of an old friend, Harry Lime.",
    "language": [
        "English",
        "German",
        "Russian"
    ],
    "country": "UK",
    "awards": "Won 1 Oscar. Another 4 wins & 4 nominations.",
    "poster": "http:\/\/ia.media-imdb.com\/images\/M\/MV5BMjMwNzMzMTQ0Ml5BMl5BanBnXkFtZTgwNjExMzUwNjE@._V1_SX300.jpg",
    "metascore": "N\/A"
}