{
    "imdbRating": 8.5,
    "imdbVotes": 133299,
    "imdbId": "tt0043014",
    "title": "Sunset Blvd.",
    "year": 1950,
    "rated": "NOT RATED",
    "released": "25 Aug 1950",
    "runtime": "110 min",
    "genre": [
        "Drama",
        "Film-Noir"
    ],
    "director": "Billy Wilder",
    "writer": "Charles Brackett, Billy Wilder, D.M. Marshman Jr.",
    "actors": [
        ""
    ],
    "plot": "A hack screenwriter writes a screenplay for a former silent-film star who has faded into Hollywood obscurity.",
    "language": [
        "English"
    ],
    "country": "USA",
    "awards": "Won 3 Oscars. Another 15 wins & 18 nominations.",
    "poster": "http:\/\/ia.media-imdb.com\/images\/M\/MV5BMTc3NDYzODAwNV5BMl5BanBnXkFtZTgwODg1MTczMTE@._V1_SX300.jpg",
    "metascore": "N\/A"
}